{
	"name": "Emp2",
	"properties": {
		"linkedServiceName": {
			"referenceName": "LinkedService_StorageDemo",
			"type": "LinkedServiceReference"
		},
		"annotations": [],
		"type": "DelimitedText",
		"typeProperties": {
			"location": {
				"type": "AzureBlobStorageLocation",
				"fileName": "employee (2).csv",
				"folderPath": "input",
				"container": "adfdemo"
			},
			"columnDelimiter": ",",
			"escapeChar": "\\",
			"firstRowAsHeader": true,
			"quoteChar": "\""
		},
		"schema": [
			{
				"name": "empid",
				"type": "String"
			},
			{
				"name": "name",
				"type": "String"
			},
			{
				"name": "salary",
				"type": "String"
			},
			{
				"name": "department",
				"type": "String"
			}
		]
	}
}